[
    {
        "elements": [
            "B",
            "N"
            "C"
        ],
        "file": "BNC.tersoff"
    },
    {
        "elements": [
            "Ga",
            "N"
        ],
        "file": "GaN.tersoff"
    },
    {
        "elements": [
            "Si",
            "C"
        ],
        "file": "SiC_1989.tersoff"
    },
    {
        "elements": [
            "Si",
            "C"
        ],
        "file": "SiC_1990.tersoff"
    },
    {
        "elements": [
            "Si",
            "C"
        ],
        "file": "SiC_1994.tersoff"
    },
    {
        "elements": [
            "Si",
            "C"
        ],
        "file": "SiC_Erhart-Albe.tersoff"
    },
    {
        "elements": [
            "Si",
            "C"
        ],
        "file": "SiC.tersoff"
    },
    {
        "elements": [
            "Si",
        ],
        "file": "Si.tersoff"
    },
    {
        "elements": [
            "Si",
            "O"
        ],
        "file": "SiO.tersoff"
    },
    {
        "elements": [
            "Si",
            "C",
            "Ge"
        ],
        "file": "SiCGe.tersoff"
    },
]
